pycmox.cpython-36m-x86_64-linux-gnu.so
pycmox-0.2.4.dist-info/METADATA
pycmox-0.2.4.dist-info/WHEEL
pycmox-0.2.4.dist-info/RECORD
pycmox-0.2.4.dist-info/top_level.txt
pycmox-0.2.4.dist-info/LICENSE
