Metadata-Version: 2.4
Name: pycmox
Version: 0.2.4
Summary: A Python wrapper for lmox
Home-page: https://curl.sai.msu.ru/hg/pycmox/
Author: Matwey V. Kornilov
Author-email: matwey.kornilov@gmail.com
License: LGPL-3.0-or-later
Classifier: Programming Language :: Python
Classifier: Programming Language :: Python :: 3
Requires-Python: >=3.6
License-File: LICENSE
Dynamic: license-file
